UTRManager/UTRLibrary.py
UTRManager/__init__.py
UTRManager-1.0.1.dist-info/METADATA
UTRManager-1.0.1.dist-info/WHEEL
UTRManager-1.0.1.dist-info/top_level.txt
UTRManager-1.0.1.dist-info/RECORD
