Metadata-Version: 2.1
Name: UTRManager
Version: 1.0.1
Summary: Receive data from UTR device
Author: Takaya
Author-email: sashin_ranjitkar@takaya.co.jp
License: UNKNOWN
Platform: UNKNOWN
Classifier: Programming Language :: Python :: 3.6
Classifier: Programming Language :: Python :: 3.7
Classifier: Programming Language :: Python :: 3.8
Classifier: Programming Language :: Python :: 3.9
Classifier: License :: OSI Approved :: MIT License
Classifier: Operating System :: OS Independent
